gs_visual_tool/__init__.py
gs_visual_tool/environment_detection.py
gs_visual_tool/render.py
gs_visual_tool/run.py
gs_visual_tool/server.py
gs_visual_tool/template/index.html
gs_visual_tool/template/modeling.html
gs_visual_tool/template/querying.html
gs_visual_tool-0.1.1.dist-info/METADATA
gs_visual_tool-0.1.1.dist-info/WHEEL
gs_visual_tool-0.1.1.dist-info/top_level.txt
gs_visual_tool-0.1.1.dist-info/RECORD
